roc/__init__.py
roc/rpl/__init__.py
roc/rpl/commands.py
roc/rpl/compressed/__init__.py
roc/rpl/compressed/lfr.py
roc/rpl/compressed/tds.py
roc/rpl/compressed/utils.py
roc/rpl/constants.py
roc/rpl/descriptor.json
roc/rpl/exceptions.py
roc/rpl/packet_parser/__init__.py
roc/rpl/packet_parser/base_packet.py
roc/rpl/packet_parser/extended_data.py
roc/rpl/packet_parser/packet_cache.py
roc/rpl/packet_parser/packet_parser.py
roc/rpl/packet_parser/palisade.py
roc/rpl/packet_parser/parser/__init__.py
roc/rpl/packet_parser/parser/identify_packets.pyx
roc/rpl/packet_parser/parser/parse_packets.pyx
roc/rpl/packet_parser/raw_data.py
roc/rpl/packet_parser/transfer_function.py
roc/rpl/packet_structure/__init__.py
roc/rpl/packet_structure/data.pxd
roc/rpl/packet_structure/data.pyx
roc/rpl/packet_structure/header.pxd
roc/rpl/packet_structure/header.pyx
roc/rpl/packet_structure/parameter.pxd
roc/rpl/packet_structure/parameter.pyx
roc/rpl/packet_structure/type_conversion.c
roc/rpl/packet_structure/type_conversion.h
roc/rpl/paths.py
roc/rpl/rice/.ycm_extra_conf.py
roc/rpl/rice/GsrNotExportedHeader.h
roc/rpl/rice/GsrPreprocessMode.h
roc/rpl/rice/GsrRiceCompress.cpp
roc/rpl/rice/GsrRiceCompress.h
roc/rpl/rice/GsrRiceMacroAndConst.h
roc/rpl/rice/GsrRiceUncompress.cpp
roc/rpl/rice/GsrRiceUncompress.h
roc/rpl/rice/RiceWrapper.cpp
roc/rpl/rice/RiceWrapper.h
roc/rpl/rice/__init__.pxd
roc/rpl/rice/__init__.py
roc/rpl/rice/crice.pxd
roc/rpl/rice/rice.pyx
roc/rpl/tasks/__init__.py
roc/rpl/tasks/identify_packets.py
roc/rpl/tasks/packets_to_json.py
roc/rpl/tasks/parse_packets.py
roc/rpl/tasks/tools.py
roc/rpl/tests/__init__.py
roc/rpl/tests/data/data.dat
roc/rpl/tests/data/test_packets_to_json.json
roc/rpl/tests/data/test_packets_to_json_header_only.json
roc/rpl/tests/test_packets_to_json.py
roc/rpl/tests/test_rice.py
roc/rpl/tests/test_rpl_extraction.py
roc/rpl/tests/test_time.py
roc/rpl/time/__init__.py
roc/rpl/time/leapsec.py
roc/rpl/time/spice.py
roc/rpl/time/time.py
roc_rpl-1.7.1.dist-info/LICENSE
roc_rpl-1.7.1.dist-info/METADATA
roc_rpl-1.7.1.dist-info/WHEEL
roc_rpl-1.7.1.dist-info/RECORD
