Metadata-Version: 2.3
Name: roc-rpl
Version: 1.7.1
Summary: RPW Packet parsing Library (RPL): a plugin for the RPW TM/TC packet analysis
Home-page: https://gitlab.obspm.fr/ROC/Pipelines/Plugins/RPL
License: CeCILL 2.1
Author: ROC Team
Author-email: roc.support@sympa.obspm.fr
Requires-Python: >=3.9,<4
Classifier: License :: Other/Proprietary License
Classifier: Programming Language :: Python :: 3
Classifier: Programming Language :: Python :: 3.9
Classifier: Programming Language :: Python :: 3.10
Classifier: Programming Language :: Python :: 3.11
Classifier: Programming Language :: Python :: 3.12
Classifier: Programming Language :: Python :: 3.13
Requires-Dist: cython (>=3,<4)
Requires-Dist: numpy (>=1.20,<3)
Requires-Dist: poppy-core (>0.12.0)
Requires-Dist: poppy-pop (>0.12.0)
Requires-Dist: roc-idb (>=1.0,<2.0)
Requires-Dist: spice_manager
Project-URL: Repository, https://gitlab.obspm.fr/ROC/Pipelines/Plugins/RPL
